tgtg/__init__.py
tgtg/exceptions.py
tgtg/google_play_scraper.py
tgtg-0.18.4.dist-info/LICENCE
tgtg-0.18.4.dist-info/METADATA
tgtg-0.18.4.dist-info/WHEEL
tgtg-0.18.4.dist-info/RECORD
