Metadata-Version: 2.3
Name: tgtg
Version: 0.18.4
Summary: Unoffical python client for TooGoodToGo API
Author: Anthony Hivert
Author-email: anthony.hivert@gmail.com
Requires-Python: >=3.9,<4.0
Classifier: Programming Language :: Python :: 3
Classifier: Programming Language :: Python :: 3.9
Classifier: Programming Language :: Python :: 3.10
Classifier: Programming Language :: Python :: 3.11
Classifier: Programming Language :: Python :: 3.12
Classifier: Programming Language :: Python :: 3.13
Requires-Dist: requests (>=2.27.1,<3.0.0)
Project-URL: Repository, https://github.com/ahivert/tgtg-python
